chartgenerator/__init__.py
chartgenerator/chartgenerator.py
chartgenerator-0.1a19.dist-info/METADATA
chartgenerator-0.1a19.dist-info/RECORD
chartgenerator-0.1a19.dist-info/WHEEL
chartgenerator-0.1a19.dist-info/top_level.txt
