Metadata-Version: 2.1
Name: chartgenerator
Version: 0.1a19
Summary: Candlestick chart generator and support/resistance calculator for market data using Plot.ly and peakutils.
Home-page: https://github.com/hmallen/chartgenerator
Author: Hunter M. Allen
Author-email: allenhm@gmail.com
License: MIT
Keywords: chart,generator
Platform: UNKNOWN
Classifier: Programming Language :: Python :: 3
Classifier: License :: OSI Approved :: MIT License
Classifier: Operating System :: OS Independent
Requires-Dist: numpy
Requires-Dist: numpyencoder
Requires-Dist: pandas
Requires-Dist: peakutils
Requires-Dist: plotly
